{
  "id": "nature-2",
  "category": "nature",
  "categoryName": "Luonto",
  "tier": 2,
  "words": [
    "lago",
    "playa",
    "bosque",
    "tierra",
    "piedra",
    "fuego",
    "el parque natural",
    "la ardilla",
    "el ciervo",
    "el camping",
    "la tienda de campaña",
    "poner la tienda",
    "el paraguas",
    "nublado",
    "calor"
  ],
  "phrases": [
    "1190842",
    "534385",
    "483435",
    "456302",
    "2110643",
    "5864190",
    "519546",
    "5939751",
    "1392137",
    "1520299",
    "736033",
    "3118317",
    "1637534",
    "1698639",
    "3100711",
    "3773673",
    "514320",
    "1172043",
    "456172",
    "1306029",
    "2239962"
  ]
}